publish.sh
anysd/__init__.py
anysd/conf.py
anysd/config.toml
anysd/main.py
anysd/utils.py
anysd-1.2.5.dist-info/LICENSE
anysd-1.2.5.dist-info/METADATA
anysd-1.2.5.dist-info/WHEEL
anysd-1.2.5.dist-info/RECORD
