Metadata-Version: 2.1
Name: anysd
Version: 1.2.5
Summary: For building ussd applications faster, with navigation management out of the box
License: MIT
Keywords: ussd,navigation
Author: Somwaki
Author-email: somwaki@gmail.com
Requires-Python: >=3.7
Classifier: License :: OSI Approved :: MIT License
Classifier: Programming Language :: Python
Classifier: Programming Language :: Python :: 3
Classifier: Programming Language :: Python :: 3.7
Classifier: Programming Language :: Python :: 3.8
Classifier: Programming Language :: Python :: 3.9
Classifier: Programming Language :: Python :: 3.10
Classifier: Programming Language :: Python :: 3.11
Classifier: Programming Language :: Python :: 3.12
Classifier: Programming Language :: Python :: 3.13
Requires-Dist: anytree (<=2.8.0)
Requires-Dist: black (>=22.1.0)
Requires-Dist: bumpver (>=2020.1108)
Requires-Dist: cfg-load (<=0.9.0)
Requires-Dist: isort (>=5.9.0)
Requires-Dist: redis (>=4.0.0)
Project-URL: Homepage, https://github.com/somwaki/anysd
